LICENSE.txt
MANIFEST.in
README
setup.cfg
setup.py
app/__init__.py
app/config_tool.py
config_tool.egg-info/PKG-INFO
config_tool.egg-info/SOURCES.txt
config_tool.egg-info/dependency_links.txt
config_tool.egg-info/entry_points.txt
config_tool.egg-info/requires.txt
config_tool.egg-info/top_level.txt