Metadata-Version: 1.1
Name: config-tool
Version: 0.0.11
Summary: config_tool is a simple configuration management tool for JSON files.
Home-page: https://bitbucket.org/x684867/config-tool/wiki/Home
Author: Sam Caldwell
Author-email: mail@samcaldwell.net
License: MIT
Keywords: json config read write validate configuration utility
Platform: UNKNOWN
Classifier: Development Status :: 3 - Alpha
Classifier: Intended Audience :: Developers
Classifier: Intended Audience :: Information Technology
Classifier: Intended Audience :: System Administrators
Classifier: Topic :: Software Development :: Build Tools
Classifier: License :: OSI Approved :: MIT License
Classifier: Programming Language :: Python :: 2.7
Classifier: Programming Language :: Python :: 3
Classifier: Programming Language :: Python :: 3.3
Classifier: Programming Language :: Python :: 3.4
Classifier: Programming Language :: Python :: 3.5
